blockchainpype/__init__.py
blockchainpype/evm/__init__.py
blockchainpype/evm/asset.py
blockchainpype/evm/blockchain/__init__.py
blockchainpype/evm/blockchain/blockchain.py
blockchainpype/evm/blockchain/configuration.py
blockchainpype/evm/blockchain/gas.py
blockchainpype/evm/blockchain/identifier.py
blockchainpype/evm/blockchain/providers/__init__.py
blockchainpype/evm/blockchain/providers/limited.py
blockchainpype/evm/blockchain/providers/multiple.py
blockchainpype/evm/dapp/__init__.py
blockchainpype/evm/dapp/abi.py
blockchainpype/evm/dapp/contract.py
blockchainpype/evm/dapp/erc20.py
blockchainpype/evm/explorer/__init__.py
blockchainpype/evm/explorer/etherscan.py
blockchainpype/evm/transaction.py
blockchainpype/evm/wallet/__init__.py
blockchainpype/evm/wallet/identifier.py
blockchainpype/evm/wallet/signer.py
blockchainpype/evm/wallet/wallet.py
blockchainpype/factory.py
blockchainpype/ipfs.py
blockchainpype/solana/asset.py
blockchainpype/solana/blockchain/__init__.py
blockchainpype/solana/blockchain/blockchain.py
blockchainpype/solana/blockchain/configuration.py
blockchainpype/solana/blockchain/identifier.py
blockchainpype/solana/dapp/__init__.py
blockchainpype/solana/dapp/idl.py
blockchainpype/solana/dapp/program.py
blockchainpype/solana/dapp/token.py
blockchainpype/solana/explorer/__init__.py
blockchainpype/solana/explorer/solscan.py
blockchainpype/solana/transaction.py
blockchainpype/solana/wallet/identifier.py
blockchainpype/solana/wallet/signer.py
blockchainpype/solana/wallet/wallet.py
blockchainpype-0.1.1.dist-info/LICENSE
blockchainpype-0.1.1.dist-info/METADATA
blockchainpype-0.1.1.dist-info/WHEEL
blockchainpype-0.1.1.dist-info/RECORD
