Metadata-Version: 2.1
Name: blockchainpype
Version: 0.1.1
Summary: BlockchainPype is a Python library for interacting with multiple blockchain networks.
Author: Gianluca Pagliara
Author-email: pagliara.gianluca@gmail.com
Requires-Python: >=3.13,<4.0
Classifier: Programming Language :: Python :: 3
Classifier: Programming Language :: Python :: 3.13
Requires-Dist: financepype (>=0.1.0,<0.2.0)
Requires-Dist: solana (>=0.36.3,<0.37.0)
Requires-Dist: solders (>=0.23.0,<0.24.0)
Requires-Dist: web3 (>=7.6.1,<8.0.0)
